pymonday/__init__.py
pymonday/columns.py
pymonday/monday_api_client.py
pymonday-2.1.9.dist-info/LICENSE
pymonday-2.1.9.dist-info/METADATA
pymonday-2.1.9.dist-info/WHEEL
pymonday-2.1.9.dist-info/top_level.txt
pymonday-2.1.9.dist-info/RECORD
