Metadata-Version: 2.1
Name: pymonday
Version: 2.1.9
Summary: PyMonday is a monday.com API Python Client Library, compatible with API version 2023-10 and later.
License-File: LICENSE
Requires-Dist: httpx
Requires-Dist: python-dotenv
Requires-Dist: PyYAML
Requires-Dist: asyncio
